psmpa/__init__.py
psmpa/default.py
psmpa/place_seqs.py
psmpa/psmpa1.py
psmpa/psmpa2.py
psmpa/psmpa_fungi.py
psmpa/util.py
psmpa/wrap_hsp.py
psmpa/Rscripts/castor_hsp.R
psmpa/Rscripts/castor_nsti.R
psmpa/default_files/psmpa1/16S.tsv.gz
psmpa/default_files/psmpa1/bgc.tsv.gz
psmpa/default_files/psmpa1/pro_ref/pro_ref.fna
psmpa/default_files/psmpa1/pro_ref/pro_ref.hmm
psmpa/default_files/psmpa1/pro_ref/pro_ref.model
psmpa/default_files/psmpa1/pro_ref/pro_ref.raxml_info
psmpa/default_files/psmpa1/pro_ref/pro_ref.tre
psmpa/default_files/psmpa2/psmpa2_database_16S_count.tsv.gz
psmpa/default_files/psmpa2/psmpa2_database_lineage.tsv.gz
psmpa/default_files/psmpa2/psmpa2_database_mean_float.tsv.gz
psmpa/default_files/psmpa2/psmpa2_database_mean_int.tsv.gz
psmpa/default_files/psmpa2/psmpa2_database_median_float.tsv.gz
psmpa/default_files/psmpa2/psmpa2_database_median_int.tsv.gz
psmpa/default_files/psmpa2/blast_db/rna.ndb
psmpa/default_files/psmpa2/blast_db/rna.nhr
psmpa/default_files/psmpa2/blast_db/rna.nin
psmpa/default_files/psmpa2/blast_db/rna.not
psmpa/default_files/psmpa2/blast_db/rna.nsq
psmpa/default_files/psmpa2/blast_db/rna.ntf
psmpa/default_files/psmpa2/blast_db/rna.nto
psmpa/default_files/psmpa_fungi/psmpa_fungi_database_default.tsv.gz
psmpa/default_files/psmpa_fungi/blast_db/ref18S.ndb
psmpa/default_files/psmpa_fungi/blast_db/ref18S.nhr
psmpa/default_files/psmpa_fungi/blast_db/ref18S.nin
psmpa/default_files/psmpa_fungi/blast_db/ref18S.not
psmpa/default_files/psmpa_fungi/blast_db/ref18S.nsq
psmpa/default_files/psmpa_fungi/blast_db/ref18S.ntf
psmpa/default_files/psmpa_fungi/blast_db/ref18S.nto
psmpa-2.0.0.data/scripts/psmpa-fungi
psmpa-2.0.0.data/scripts/psmpa1
psmpa-2.0.0.data/scripts/psmpa2
psmpa-2.0.0.dist-info/LICENSE
psmpa-2.0.0.dist-info/METADATA
psmpa-2.0.0.dist-info/WHEEL
psmpa-2.0.0.dist-info/top_level.txt
psmpa-2.0.0.dist-info/RECORD
